[
  {
    "date": "2019/09/29",
    "heure": "02:38:18",
    "lon": "4.5348",
    "lat": "41.706175",
    "DateTime": null
  },
  {
    "date": "2019/09/29",
    "heure": "03:52:07",
    "lon": "2.53551",
    "lat": "40.928294",
    "DateTime": null
  },
  {
    "date": "2019/09/29",
    "heure": "05:18:01",
    "lon": "3.194704",
    "lat": "42.078192",
    "DateTime": null
  },
  {
    "date": "2019/09/29",
    "heure": "06:43:37",
    "lon": "0.722595",
    "lat": "48.782841",
    "DateTime": null
  },
  {
    "date": "2019/09/29",
    "heure": "07:22:25",
    "lon": "-3.256543",
    "lat": "46.608239",
    "DateTime": null
  },
  {
    "date": "2019/09/29",
    "heure": "11:42:27",
    "lon": "-1.696171",
    "lat": "46.659658",
    "DateTime": null
  },
  {
    "date": "2019/09/29",
    "heure": "19:24:18",
    "lon": "1.769606",
    "lat": "52.549617",
    "DateTime": null
  },
  {
    "date": "2019/09/29",
    "heure": "19:24:18",
    "lon": "1.803469",
    "lat": "52.546317",
    "DateTime": null
  },
  {
    "date": "2019/09/29",
    "heure": "19:24:18",
    "lon": "1.833619",
    "lat": "52.523534",
    "DateTime": null
  },
  {
    "date": "2019/09/29",
    "heure": "19:24:18",
    "lon": "1.841783",
    "lat": "52.520155",
    "DateTime": null
  },
  {
    "date": "2019/09/29",
    "heure": "19:24:18",
    "lon": "1.844039",
    "lat": "52.521385",
    "DateTime": null
  },
  {
    "date": "2019/09/29",
    "heure": "19:24:18",
    "lon": "1.846513",
    "lat": "52.543015",
    "DateTime": null
  },
  {
    "date": "2019/09/29",
    "heure": "19:24:18",
    "lon": "1.849387",
    "lat": "52.523374",
    "DateTime": null
  },
  {
    "date": "2019/09/29",
    "heure": "19:24:18",
    "lon": "1.849462",
    "lat": "52.52824",
    "DateTime": null
  },
  {
    "date": "2019/09/29",
    "heure": "19:24:18",
    "lon": "1.980064",
    "lat": "52.390962",
    "DateTime": null
  },
  {
    "date": "2019/09/29",
    "heure": "20:09:15",
    "lon": "4.990608",
    "lat": "50.778668",
    "DateTime": null
  },
  {
    "date": "2019/09/29",
    "heure": "20:09:15",
    "lon": "5.004182",
    "lat": "50.797173",
    "DateTime": null
  },
  {
    "date": "2019/09/29",
    "heure": "20:09:15",
    "lon": "5.012283",
    "lat": "50.797888",
    "DateTime": null
  },
  {
    "date": "2019/09/29",
    "heure": "20:09:15",
    "lon": "5.138581",
    "lat": "50.790612",
    "DateTime": null
  },
  {
    "date": "2019/09/29",
    "heure": "21:31:22",
    "lon": "6.402271",
    "lat": "51.013814",
    "DateTime": null
  },
  {
    "date": "2019/09/29",
    "heure": "21:31:22",
    "lon": "6.406875",
    "lat": "51.012394",
    "DateTime": null
  },
  {
    "date": "2019/09/29",
    "heure": "21:31:22",
    "lon": "6.414413",
    "lat": "51.008571",
    "DateTime": null
  },
  {
    "date": "2019/09/29",
    "heure": "21:31:22",
    "lon": "6.416191",
    "lat": "51.006289",
    "DateTime": null
  },
  {
    "date": "2019/09/29",
    "heure": "21:43:50",
    "lon": "7.156961",
    "lat": "51.439672",
    "DateTime": null
  },
  {
    "date": "2019/09/29",
    "heure": "21:43:50",
    "lon": "7.163732",
    "lat": "51.445494",
    "DateTime": null
  },
  {
    "date": "2019/09/29",
    "heure": "22:05:48",
    "lon": "3.99807",
    "lat": "41.863864",
    "DateTime": null
  },
  {
    "date": "2019/09/29",
    "heure": "22:14:30",
    "lon": "7.638121",
    "lat": "51.534796",
    "DateTime": null
  },
  {
    "date": "2019/09/29",
    "heure": "22:14:30",
    "lon": "7.905497",
    "lat": "51.635197",
    "DateTime": null
  },
  {
    "date": "2019/09/29",
    "heure": "22:20:21",
    "lon": "7.752962",
    "lat": "51.538575",
    "DateTime": null
  },
  {
    "date": "2019/09/29",
    "heure": "22:21:23",
    "lon": "8.107694",
    "lat": "50.967571",
    "DateTime": null
  },
  {
    "date": "2019/09/29",
    "heure": "22:21:23",
    "lon": "8.116592",
    "lat": "50.969392",
    "DateTime": null
  },
  {
    "date": "2019/09/29",
    "heure": "22:29:13",
    "lon": "8.006219",
    "lat": "51.545799",
    "DateTime": null
  },
  {
    "date": "2019/09/29",
    "heure": "22:36:12",
    "lon": "8.07782",
    "lat": "51.611791",
    "DateTime": null
  },
  {
    "date": "2019/09/29",
    "heure": "22:36:12",
    "lon": "8.40282",
    "lat": "51.556547",
    "DateTime": null
  },
  {
    "date": "2019/09/29",
    "heure": "22:44:06",
    "lon": "8.346742",
    "lat": "51.600264",
    "DateTime": null
  },
  {
    "date": "2019/09/29",
    "heure": "22:50:45",
    "lon": "7.846179",
    "lat": "50.914447",
    "DateTime": null
  },
  {
    "date": "2019/09/29",
    "heure": "22:50:45",
    "lon": "7.859739",
    "lat": "50.916133",
    "DateTime": null
  },
  {
    "date": "2019/09/29",
    "heure": "22:50:45",
    "lon": "7.861851",
    "lat": "50.914827",
    "DateTime": null
  },
  {
    "date": "2019/09/29",
    "heure": "22:50:45",
    "lon": "7.862978",
    "lat": "50.918167",
    "DateTime": null
  },
  {
    "date": "2019/09/29",
    "heure": "22:50:45",
    "lon": "7.870112",
    "lat": "50.923978",
    "DateTime": null
  },
  {
    "date": "2019/09/29",
    "heure": "22:56:05",
    "lon": "8.930643",
    "lat": "51.744599",
    "DateTime": null
  },
  {
    "date": "2019/09/29",
    "heure": "22:56:05",
    "lon": "8.948617",
    "lat": "51.742465",
    "DateTime": null
  },
  {
    "date": "2019/09/29",
    "heure": "23:00:05",
    "lon": "8.014934",
    "lat": "50.68367",
    "DateTime": null
  },
  {
    "date": "2019/09/29",
    "heure": "23:00:05",
    "lon": "8.107447",
    "lat": "50.643463",
    "DateTime": null
  },
  {
    "date": "2019/09/29",
    "heure": "23:00:05",
    "lon": "8.115606",
    "lat": "50.616911",
    "DateTime": null
  },
  {
    "date": "2019/09/29",
    "heure": "23:00:05",
    "lon": "8.115741",
    "lat": "50.654248",
    "DateTime": null
  },
  {
    "date": "2019/09/29",
    "heure": "23:00:05",
    "lon": "8.118077",
    "lat": "50.648279",
    "DateTime": null
  },
  {
    "date": "2019/09/29",
    "heure": "23:00:05",
    "lon": "8.121515",
    "lat": "50.649407",
    "DateTime": null
  },
  {
    "date": "2019/09/29",
    "heure": "23:00:05",
    "lon": "8.122923",
    "lat": "50.644892",
    "DateTime": null
  },
  {
    "date": "2019/09/29",
    "heure": "23:00:05",
    "lon": "8.123582",
    "lat": "50.646524",
    "DateTime": null
  },
  {
    "date": "2019/09/29",
    "heure": "23:00:05",
    "lon": "8.12378",
    "lat": "50.659685",
    "DateTime": null
  },
  {
    "date": "2019/09/29",
    "heure": "23:00:05",
    "lon": "8.124553",
    "lat": "50.650962",
    "DateTime": null
  },
  {
    "date": "2019/09/29",
    "heure": "23:00:05",
    "lon": "8.126499",
    "lat": "50.64749",
    "DateTime": null
  },
  {
    "date": "2019/09/29",
    "heure": "23:00:05",
    "lon": "8.130715",
    "lat": "50.650228",
    "DateTime": null
  },
  {
    "date": "2019/09/29",
    "heure": "23:00:05",
    "lon": "8.131114",
    "lat": "50.613582",
    "DateTime": null
  },
  {
    "date": "2019/09/29",
    "heure": "23:00:05",
    "lon": "8.131512",
    "lat": "50.645511",
    "DateTime": null
  },
  {
    "date": "2019/09/29",
    "heure": "23:00:05",
    "lon": "8.134838",
    "lat": "50.654614",
    "DateTime": null
  },
  {
    "date": "2019/09/29",
    "heure": "23:01:51",
    "lon": "8.97262",
    "lat": "51.78085",
    "DateTime": null
  },
  {
    "date": "2019/09/29",
    "heure": "23:01:51",
    "lon": "8.974139",
    "lat": "51.783274",
    "DateTime": null
  },
  {
    "date": "2019/09/29",
    "heure": "23:01:51",
    "lon": "8.977714",
    "lat": "51.753559",
    "DateTime": null
  },
  {
    "date": "2019/09/29",
    "heure": "23:01:51",
    "lon": "8.98231",
    "lat": "51.789785",
    "DateTime": null
  },
  {
    "date": "2019/09/29",
    "heure": "23:01:51",
    "lon": "8.983257",
    "lat": "51.770492",
    "DateTime": null
  },
  {
    "date": "2019/09/29",
    "heure": "23:01:51",
    "lon": "8.988969",
    "lat": "51.768497",
    "DateTime": null
  },
  {
    "date": "2019/09/29",
    "heure": "23:01:51",
    "lon": "8.991928",
    "lat": "51.79482",
    "DateTime": null
  },
  {
    "date": "2019/09/29",
    "heure": "23:01:51",
    "lon": "9.06926",
    "lat": "51.737446",
    "DateTime": null
  },
  {
    "date": "2019/09/29",
    "heure": "23:13:50",
    "lon": "2.25895",
    "lat": "40.881299",
    "DateTime": null
  },
  {
    "date": "2019/09/29",
    "heure": "23:17:29",
    "lon": "8.112947",
    "lat": "50.652267",
    "DateTime": null
  },
  {
    "date": "2019/09/29",
    "heure": "23:17:29",
    "lon": "8.113287",
    "lat": "50.646455",
    "DateTime": null
  },
  {
    "date": "2019/09/29",
    "heure": "23:17:29",
    "lon": "8.143118",
    "lat": "50.652974",
    "DateTime": null
  },
  {
    "date": "2019/09/29",
    "heure": "23:19:54",
    "lon": "8.130391",
    "lat": "50.630878",
    "DateTime": null
  },
  {
    "date": "2019/09/29",
    "heure": "23:19:54",
    "lon": "8.147713",
    "lat": "50.670478",
    "DateTime": null
  },
  {
    "date": "2019/09/29",
    "heure": "23:19:54",
    "lon": "8.159797",
    "lat": "50.656424",
    "DateTime": null
  },
  {
    "date": "2019/09/29",
    "heure": "23:19:54",
    "lon": "8.16128",
    "lat": "50.651672",
    "DateTime": null
  },
  {
    "date": "2019/09/29",
    "heure": "23:19:54",
    "lon": "8.173517",
    "lat": "50.646391",
    "DateTime": null
  },
  {
    "date": "2019/09/29",
    "heure": "23:58:42",
    "lon": "9.479073",
    "lat": "42.040279",
    "DateTime": null
  }
]