[
  {
    "date": "2018/01/12",
    "heure": "01:58",
    "lon": "9.748800",
    "lat": "41.191800",
    "DateTime": null
  },
  {
    "date": "2018/01/12",
    "heure": "18:15",
    "lon": "6.887700",
    "lat": "41.024300",
    "DateTime": null
  },
  {
    "date": "2018/01/12",
    "heure": "18:30",
    "lon": "6.767800",
    "lat": "40.961600",
    "DateTime": null
  },
  {
    "date": "2018/01/12",
    "heure": "18:32",
    "lon": "6.692800",
    "lat": "40.887300",
    "DateTime": null
  },
  {
    "date": "2018/01/12",
    "heure": "18:42",
    "lon": "6.751500",
    "lat": "40.876200",
    "DateTime": null
  },
  {
    "date": "2018/01/12",
    "heure": "18:42",
    "lon": "6.761300",
    "lat": "40.659000",
    "DateTime": null
  },
  {
    "date": "2018/01/12",
    "heure": "21:40",
    "lon": "5.251100",
    "lat": "40.597100",
    "DateTime": null
  },
  {
    "date": "2018/01/12",
    "heure": "21:46",
    "lon": "6.676000",
    "lat": "40.576100",
    "DateTime": null
  },
  {
    "date": "2018/01/12",
    "heure": "21:46",
    "lon": "6.737400",
    "lat": "40.604400",
    "DateTime": null
  },
  {
    "date": "2018/01/12",
    "heure": "21:48",
    "lon": "6.718100",
    "lat": "40.607300",
    "DateTime": null
  },
  {
    "date": "2018/01/12",
    "heure": "21:48",
    "lon": "6.735800",
    "lat": "40.542100",
    "DateTime": null
  },
  {
    "date": "2018/01/12",
    "heure": "21:48",
    "lon": "6.739100",
    "lat": "40.468600",
    "DateTime": null
  },
  {
    "date": "2018/01/12",
    "heure": "21:48",
    "lon": "6.748200",
    "lat": "40.457900",
    "DateTime": null
  }
]