[
  {
    "date": "2019/12/01",
    "heure": "02:42:48",
    "lon": "-4.92407",
    "lat": "44.7972",
    "DateTime": null
  },
  {
    "date": "2019/12/01",
    "heure": "04:10:50",
    "lon": "-2.951762",
    "lat": "44.669674",
    "DateTime": null
  },
  {
    "date": "2019/12/01",
    "heure": "04:10:50",
    "lon": "-2.952604",
    "lat": "44.674002",
    "DateTime": null
  },
  {
    "date": "2019/12/01",
    "heure": "04:10:50",
    "lon": "-2.959053",
    "lat": "44.669059",
    "DateTime": null
  },
  {
    "date": "2019/12/01",
    "heure": "05:24:05",
    "lon": "-4.557966",
    "lat": "44.468697",
    "DateTime": null
  },
  {
    "date": "2019/12/01",
    "heure": "06:19:54",
    "lon": "-4.76531",
    "lat": "44.552524",
    "DateTime": null
  },
  {
    "date": "2019/12/01",
    "heure": "06:19:54",
    "lon": "-4.779839",
    "lat": "44.499264",
    "DateTime": null
  },
  {
    "date": "2019/12/01",
    "heure": "06:26:33",
    "lon": "-4.806999",
    "lat": "44.440923",
    "DateTime": null
  },
  {
    "date": "2019/12/01",
    "heure": "07:20:40",
    "lon": "5.76123",
    "lat": "44.663265",
    "DateTime": null
  },
  {
    "date": "2019/12/01",
    "heure": "07:20:40",
    "lon": "5.788653",
    "lat": "44.655099",
    "DateTime": null
  },
  {
    "date": "2019/12/01",
    "heure": "07:20:40",
    "lon": "5.790266",
    "lat": "44.643508",
    "DateTime": null
  },
  {
    "date": "2019/12/01",
    "heure": "09:32:15",
    "lon": "5.548008",
    "lat": "43.751757",
    "DateTime": null
  },
  {
    "date": "2019/12/01",
    "heure": "09:32:15",
    "lon": "5.568898",
    "lat": "43.711626",
    "DateTime": null
  },
  {
    "date": "2019/12/01",
    "heure": "09:32:15",
    "lon": "5.582594",
    "lat": "43.890592",
    "DateTime": null
  },
  {
    "date": "2019/12/01",
    "heure": "09:32:15",
    "lon": "5.864695",
    "lat": "43.610169",
    "DateTime": null
  },
  {
    "date": "2019/12/01",
    "heure": "09:37:52",
    "lon": "5.095533",
    "lat": "43.446758",
    "DateTime": null
  },
  {
    "date": "2019/12/01",
    "heure": "09:44:03",
    "lon": "-2.929513",
    "lat": "50.916837",
    "DateTime": null
  },
  {
    "date": "2019/12/01",
    "heure": "09:44:10",
    "lon": "5.550466",
    "lat": "43.786718",
    "DateTime": null
  },
  {
    "date": "2019/12/01",
    "heure": "09:44:10",
    "lon": "5.552734",
    "lat": "43.745875",
    "DateTime": null
  },
  {
    "date": "2019/12/01",
    "heure": "09:47:05",
    "lon": "5.574379",
    "lat": "43.899582",
    "DateTime": null
  },
  {
    "date": "2019/12/01",
    "heure": "09:47:05",
    "lon": "5.576499",
    "lat": "43.844198",
    "DateTime": null
  },
  {
    "date": "2019/12/01",
    "heure": "09:47:05",
    "lon": "5.608435",
    "lat": "43.927154",
    "DateTime": null
  },
  {
    "date": "2019/12/01",
    "heure": "09:47:05",
    "lon": "5.623047",
    "lat": "43.804787",
    "DateTime": null
  },
  {
    "date": "2019/12/01",
    "heure": "09:47:05",
    "lon": "5.644483",
    "lat": "43.842076",
    "DateTime": null
  },
  {
    "date": "2019/12/01",
    "heure": "09:47:05",
    "lon": "5.652013",
    "lat": "43.83131",
    "DateTime": null
  },
  {
    "date": "2019/12/01",
    "heure": "09:47:05",
    "lon": "5.654447",
    "lat": "43.841866",
    "DateTime": null
  },
  {
    "date": "2019/12/01",
    "heure": "09:47:05",
    "lon": "5.661385",
    "lat": "43.824605",
    "DateTime": null
  },
  {
    "date": "2019/12/01",
    "heure": "09:47:05",
    "lon": "5.676825",
    "lat": "43.821824",
    "DateTime": null
  },
  {
    "date": "2019/12/01",
    "heure": "09:47:05",
    "lon": "5.800654",
    "lat": "43.983354",
    "DateTime": null
  },
  {
    "date": "2019/12/01",
    "heure": "09:48:14",
    "lon": "5.64632",
    "lat": "43.865234",
    "DateTime": null
  },
  {
    "date": "2019/12/01",
    "heure": "09:48:14",
    "lon": "5.654578",
    "lat": "43.822891",
    "DateTime": null
  },
  {
    "date": "2019/12/01",
    "heure": "09:48:14",
    "lon": "5.665582",
    "lat": "43.841997",
    "DateTime": null
  },
  {
    "date": "2019/12/01",
    "heure": "09:48:14",
    "lon": "5.666957",
    "lat": "43.82006",
    "DateTime": null
  },
  {
    "date": "2019/12/01",
    "heure": "09:48:14",
    "lon": "5.675045",
    "lat": "43.824013",
    "DateTime": null
  },
  {
    "date": "2019/12/01",
    "heure": "09:48:14",
    "lon": "5.677166",
    "lat": "43.830065",
    "DateTime": null
  },
  {
    "date": "2019/12/01",
    "heure": "09:48:14",
    "lon": "5.679638",
    "lat": "43.812112",
    "DateTime": null
  },
  {
    "date": "2019/12/01",
    "heure": "09:48:14",
    "lon": "5.691513",
    "lat": "43.899447",
    "DateTime": null
  },
  {
    "date": "2019/12/01",
    "heure": "09:48:15",
    "lon": "5.667469",
    "lat": "43.840819",
    "DateTime": null
  },
  {
    "date": "2019/12/01",
    "heure": "09:48:55",
    "lon": "5.679883",
    "lat": "43.772515",
    "DateTime": null
  },
  {
    "date": "2019/12/01",
    "heure": "09:48:55",
    "lon": "5.689636",
    "lat": "43.835486",
    "DateTime": null
  },
  {
    "date": "2019/12/01",
    "heure": "09:49:59",
    "lon": "5.691029",
    "lat": "43.866594",
    "DateTime": null
  },
  {
    "date": "2019/12/01",
    "heure": "09:51:14",
    "lon": "5.6603",
    "lat": "43.875262",
    "DateTime": null
  },
  {
    "date": "2019/12/01",
    "heure": "09:51:14",
    "lon": "5.711892",
    "lat": "43.861865",
    "DateTime": null
  },
  {
    "date": "2019/12/01",
    "heure": "10:14:51",
    "lon": "-5.710074",
    "lat": "43.691378",
    "DateTime": null
  },
  {
    "date": "2019/12/01",
    "heure": "10:14:51",
    "lon": "-5.736423",
    "lat": "43.655786",
    "DateTime": null
  },
  {
    "date": "2019/12/01",
    "heure": "10:22:41",
    "lon": "6.297442",
    "lat": "44.240849",
    "DateTime": null
  },
  {
    "date": "2019/12/01",
    "heure": "10:22:41",
    "lon": "6.301677",
    "lat": "44.245741",
    "DateTime": null
  },
  {
    "date": "2019/12/01",
    "heure": "10:22:41",
    "lon": "6.301974",
    "lat": "44.249608",
    "DateTime": null
  },
  {
    "date": "2019/12/01",
    "heure": "10:22:41",
    "lon": "6.311704",
    "lat": "44.240085",
    "DateTime": null
  },
  {
    "date": "2019/12/01",
    "heure": "10:22:41",
    "lon": "6.31291",
    "lat": "44.236782",
    "DateTime": null
  },
  {
    "date": "2019/12/01",
    "heure": "10:22:41",
    "lon": "6.31343",
    "lat": "44.233117",
    "DateTime": null
  },
  {
    "date": "2019/12/01",
    "heure": "10:22:41",
    "lon": "6.332389",
    "lat": "44.166306",
    "DateTime": null
  },
  {
    "date": "2019/12/01",
    "heure": "10:22:41",
    "lon": "6.348948",
    "lat": "44.212486",
    "DateTime": null
  },
  {
    "date": "2019/12/01",
    "heure": "10:35:38",
    "lon": "-5.709863",
    "lat": "43.656282",
    "DateTime": null
  },
  {
    "date": "2019/12/01",
    "heure": "10:38:38",
    "lon": "-5.724003",
    "lat": "43.641738",
    "DateTime": null
  },
  {
    "date": "2019/12/01",
    "heure": "10:38:38",
    "lon": "-5.741139",
    "lat": "43.658079",
    "DateTime": null
  },
  {
    "date": "2019/12/01",
    "heure": "10:39:41",
    "lon": "-5.741156",
    "lat": "43.642474",
    "DateTime": null
  },
  {
    "date": "2019/12/01",
    "heure": "10:45:07",
    "lon": "5.217302",
    "lat": "43.539448",
    "DateTime": null
  },
  {
    "date": "2019/12/01",
    "heure": "10:45:07",
    "lon": "5.249831",
    "lat": "43.542838",
    "DateTime": null
  },
  {
    "date": "2019/12/01",
    "heure": "10:45:07",
    "lon": "5.250727",
    "lat": "43.531324",
    "DateTime": null
  },
  {
    "date": "2019/12/01",
    "heure": "11:59:16",
    "lon": "5.827808",
    "lat": "44.706572",
    "DateTime": null
  },
  {
    "date": "2019/12/01",
    "heure": "14:30:59",
    "lon": "-4.593724",
    "lat": "43.348431",
    "DateTime": null
  },
  {
    "date": "2019/12/01",
    "heure": "14:32:23",
    "lon": "-3.864322",
    "lat": "43.878076",
    "DateTime": null
  },
  {
    "date": "2019/12/01",
    "heure": "14:44:25",
    "lon": "-3.810649",
    "lat": "43.830365",
    "DateTime": null
  },
  {
    "date": "2019/12/01",
    "heure": "14:44:25",
    "lon": "-3.912454",
    "lat": "43.798295",
    "DateTime": null
  },
  {
    "date": "2019/12/01",
    "heure": "14:46:42",
    "lon": "-3.867763",
    "lat": "43.779554",
    "DateTime": null
  },
  {
    "date": "2019/12/01",
    "heure": "14:49:25",
    "lon": "-3.809668",
    "lat": "43.810226",
    "DateTime": null
  },
  {
    "date": "2019/12/01",
    "heure": "14:49:25",
    "lon": "-3.830499",
    "lat": "43.841718",
    "DateTime": null
  },
  {
    "date": "2019/12/01",
    "heure": "14:52:46",
    "lon": "-4.528399",
    "lat": "43.30279",
    "DateTime": null
  },
  {
    "date": "2019/12/01",
    "heure": "14:53:56",
    "lon": "-3.825321",
    "lat": "43.796407",
    "DateTime": null
  },
  {
    "date": "2019/12/01",
    "heure": "14:53:56",
    "lon": "-3.85003",
    "lat": "43.804506",
    "DateTime": null
  },
  {
    "date": "2019/12/01",
    "heure": "14:53:56",
    "lon": "-3.851783",
    "lat": "43.813685",
    "DateTime": null
  },
  {
    "date": "2019/12/01",
    "heure": "14:54:13",
    "lon": "-4.512717",
    "lat": "43.292334",
    "DateTime": null
  },
  {
    "date": "2019/12/01",
    "heure": "14:54:13",
    "lon": "-4.54519",
    "lat": "43.287207",
    "DateTime": null
  },
  {
    "date": "2019/12/01",
    "heure": "14:54:13",
    "lon": "-4.576183",
    "lat": "43.273475",
    "DateTime": null
  },
  {
    "date": "2019/12/01",
    "heure": "14:58:38",
    "lon": "-3.756006",
    "lat": "43.853084",
    "DateTime": null
  },
  {
    "date": "2019/12/01",
    "heure": "14:58:38",
    "lon": "-3.756756",
    "lat": "43.86502",
    "DateTime": null
  },
  {
    "date": "2019/12/01",
    "heure": "17:08:16",
    "lon": "6.32395",
    "lat": "43.216616",
    "DateTime": null
  },
  {
    "date": "2019/12/01",
    "heure": "17:08:16",
    "lon": "6.355667",
    "lat": "43.203691",
    "DateTime": null
  },
  {
    "date": "2019/12/01",
    "heure": "17:14:57",
    "lon": "6.417166",
    "lat": "42.967776",
    "DateTime": null
  },
  {
    "date": "2019/12/01",
    "heure": "17:32:22",
    "lon": "6.372894",
    "lat": "43.344567",
    "DateTime": null
  },
  {
    "date": "2019/12/01",
    "heure": "17:32:22",
    "lon": "6.392471",
    "lat": "43.350645",
    "DateTime": null
  },
  {
    "date": "2019/12/01",
    "heure": "17:38:57",
    "lon": "6.398572",
    "lat": "43.384166",
    "DateTime": null
  },
  {
    "date": "2019/12/01",
    "heure": "17:39:18",
    "lon": "6.557091",
    "lat": "43.539576",
    "DateTime": null
  },
  {
    "date": "2019/12/01",
    "heure": "17:39:18",
    "lon": "6.5721",
    "lat": "43.529776",
    "DateTime": null
  },
  {
    "date": "2019/12/01",
    "heure": "17:39:18",
    "lon": "6.577231",
    "lat": "43.547558",
    "DateTime": null
  },
  {
    "date": "2019/12/01",
    "heure": "17:47:31",
    "lon": "6.479077",
    "lat": "43.417778",
    "DateTime": null
  },
  {
    "date": "2019/12/01",
    "heure": "17:48:19",
    "lon": "6.590916",
    "lat": "43.619343",
    "DateTime": null
  },
  {
    "date": "2019/12/01",
    "heure": "17:48:19",
    "lon": "6.609875",
    "lat": "43.635251",
    "DateTime": null
  },
  {
    "date": "2019/12/01",
    "heure": "17:52:28",
    "lon": "6.365487",
    "lat": "43.386965",
    "DateTime": null
  },
  {
    "date": "2019/12/01",
    "heure": "17:52:28",
    "lon": "6.400816",
    "lat": "43.477565",
    "DateTime": null
  },
  {
    "date": "2019/12/01",
    "heure": "17:52:28",
    "lon": "6.474851",
    "lat": "43.475369",
    "DateTime": null
  },
  {
    "date": "2019/12/01",
    "heure": "18:07:53",
    "lon": "6.449369",
    "lat": "43.43333",
    "DateTime": null
  },
  {
    "date": "2019/12/01",
    "heure": "18:07:53",
    "lon": "6.520822",
    "lat": "43.549162",
    "DateTime": null
  },
  {
    "date": "2019/12/01",
    "heure": "18:07:53",
    "lon": "6.53283",
    "lat": "43.510011",
    "DateTime": null
  },
  {
    "date": "2019/12/01",
    "heure": "18:07:53",
    "lon": "6.5536",
    "lat": "43.512065",
    "DateTime": null
  },
  {
    "date": "2019/12/01",
    "heure": "18:07:53",
    "lon": "6.575375",
    "lat": "43.466539",
    "DateTime": null
  },
  {
    "date": "2019/12/01",
    "heure": "18:07:53",
    "lon": "7.163395",
    "lat": "43.686021",
    "DateTime": null
  },
  {
    "date": "2019/12/01",
    "heure": "18:07:53",
    "lon": "7.202117",
    "lat": "43.657982",
    "DateTime": null
  },
  {
    "date": "2019/12/01",
    "heure": "18:19:13",
    "lon": "6.640693",
    "lat": "43.645262",
    "DateTime": null
  },
  {
    "date": "2019/12/01",
    "heure": "18:21:35",
    "lon": "6.439522",
    "lat": "43.485304",
    "DateTime": null
  },
  {
    "date": "2019/12/01",
    "heure": "18:21:35",
    "lon": "6.510182",
    "lat": "43.522537",
    "DateTime": null
  },
  {
    "date": "2019/12/01",
    "heure": "18:21:35",
    "lon": "6.553335",
    "lat": "43.587381",
    "DateTime": null
  },
  {
    "date": "2019/12/01",
    "heure": "18:21:35",
    "lon": "6.604096",
    "lat": "43.586721",
    "DateTime": null
  },
  {
    "date": "2019/12/01",
    "heure": "18:21:35",
    "lon": "6.697349",
    "lat": "43.789886",
    "DateTime": null
  },
  {
    "date": "2019/12/01",
    "heure": "18:22:07",
    "lon": "6.307942",
    "lat": "44.241167",
    "DateTime": null
  },
  {
    "date": "2019/12/01",
    "heure": "18:22:07",
    "lon": "6.312167",
    "lat": "44.242171",
    "DateTime": null
  },
  {
    "date": "2019/12/01",
    "heure": "18:26:20",
    "lon": "6.627733",
    "lat": "43.605912",
    "DateTime": null
  },
  {
    "date": "2019/12/01",
    "heure": "18:43:17",
    "lon": "6.472229",
    "lat": "43.420092",
    "DateTime": null
  },
  {
    "date": "2019/12/01",
    "heure": "18:43:17",
    "lon": "6.476754",
    "lat": "43.434782",
    "DateTime": null
  },
  {
    "date": "2019/12/01",
    "heure": "18:43:17",
    "lon": "6.487532",
    "lat": "43.382141",
    "DateTime": null
  },
  {
    "date": "2019/12/01",
    "heure": "18:43:17",
    "lon": "6.488501",
    "lat": "43.34561",
    "DateTime": null
  },
  {
    "date": "2019/12/01",
    "heure": "18:43:17",
    "lon": "6.49435",
    "lat": "43.386018",
    "DateTime": null
  },
  {
    "date": "2019/12/01",
    "heure": "18:43:17",
    "lon": "6.503766",
    "lat": "43.428055",
    "DateTime": null
  },
  {
    "date": "2019/12/01",
    "heure": "18:43:17",
    "lon": "6.510808",
    "lat": "43.387761",
    "DateTime": null
  },
  {
    "date": "2019/12/01",
    "heure": "18:48:22",
    "lon": "6.114087",
    "lat": "44.128468",
    "DateTime": null
  },
  {
    "date": "2019/12/01",
    "heure": "18:48:22",
    "lon": "6.14091",
    "lat": "44.167011",
    "DateTime": null
  },
  {
    "date": "2019/12/01",
    "heure": "18:48:22",
    "lon": "6.30661",
    "lat": "44.245909",
    "DateTime": null
  },
  {
    "date": "2019/12/01",
    "heure": "18:52:44",
    "lon": "6.747812",
    "lat": "43.601651",
    "DateTime": null
  },
  {
    "date": "2019/12/01",
    "heure": "18:52:44",
    "lon": "6.984454",
    "lat": "43.880841",
    "DateTime": null
  },
  {
    "date": "2019/12/01",
    "heure": "18:52:44",
    "lon": "7.197576",
    "lat": "43.854657",
    "DateTime": null
  },
  {
    "date": "2019/12/01",
    "heure": "18:56:53",
    "lon": "6.743416",
    "lat": "43.653569",
    "DateTime": null
  },
  {
    "date": "2019/12/01",
    "heure": "19:06:27",
    "lon": "6.694911",
    "lat": "43.577095",
    "DateTime": null
  },
  {
    "date": "2019/12/01",
    "heure": "19:08:34",
    "lon": "6.431862",
    "lat": "43.204408",
    "DateTime": null
  },
  {
    "date": "2019/12/01",
    "heure": "19:10:02",
    "lon": "7.194576",
    "lat": "44.023236",
    "DateTime": null
  },
  {
    "date": "2019/12/01",
    "heure": "19:10:57",
    "lon": "6.461139",
    "lat": "43.275363",
    "DateTime": null
  },
  {
    "date": "2019/12/01",
    "heure": "19:11:46",
    "lon": "6.29302",
    "lat": "42.65584",
    "DateTime": null
  },
  {
    "date": "2019/12/01",
    "heure": "19:11:46",
    "lon": "6.423742",
    "lat": "43.348777",
    "DateTime": null
  },
  {
    "date": "2019/12/01",
    "heure": "19:11:46",
    "lon": "6.46331",
    "lat": "43.28328",
    "DateTime": null
  },
  {
    "date": "2019/12/01",
    "heure": "19:11:46",
    "lon": "6.471007",
    "lat": "43.300615",
    "DateTime": null
  },
  {
    "date": "2019/12/01",
    "heure": "19:11:46",
    "lon": "6.484169",
    "lat": "43.287095",
    "DateTime": null
  },
  {
    "date": "2019/12/01",
    "heure": "19:11:46",
    "lon": "6.498723",
    "lat": "43.300346",
    "DateTime": null
  },
  {
    "date": "2019/12/01",
    "heure": "19:11:46",
    "lon": "6.508811",
    "lat": "43.304656",
    "DateTime": null
  },
  {
    "date": "2019/12/01",
    "heure": "19:11:46",
    "lon": "6.509854",
    "lat": "43.282245",
    "DateTime": null
  },
  {
    "date": "2019/12/01",
    "heure": "19:14:39",
    "lon": "6.459968",
    "lat": "43.284983",
    "DateTime": null
  },
  {
    "date": "2019/12/01",
    "heure": "19:14:39",
    "lon": "6.463406",
    "lat": "43.297437",
    "DateTime": null
  },
  {
    "date": "2019/12/01",
    "heure": "19:14:39",
    "lon": "6.46729",
    "lat": "43.301843",
    "DateTime": null
  },
  {
    "date": "2019/12/01",
    "heure": "19:14:39",
    "lon": "6.468374",
    "lat": "43.302742",
    "DateTime": null
  },
  {
    "date": "2019/12/01",
    "heure": "19:14:39",
    "lon": "6.468789",
    "lat": "43.28554",
    "DateTime": null
  },
  {
    "date": "2019/12/01",
    "heure": "19:14:39",
    "lon": "6.487553",
    "lat": "43.277249",
    "DateTime": null
  },
  {
    "date": "2019/12/01",
    "heure": "19:16:47",
    "lon": "6.451793",
    "lat": "43.254556",
    "DateTime": null
  },
  {
    "date": "2019/12/01",
    "heure": "19:16:47",
    "lon": "6.459095",
    "lat": "43.288198",
    "DateTime": null
  },
  {
    "date": "2019/12/01",
    "heure": "19:16:47",
    "lon": "6.460097",
    "lat": "43.280786",
    "DateTime": null
  },
  {
    "date": "2019/12/01",
    "heure": "19:16:47",
    "lon": "6.471919",
    "lat": "43.332376",
    "DateTime": null
  },
  {
    "date": "2019/12/01",
    "heure": "19:16:47",
    "lon": "6.476495",
    "lat": "43.333523",
    "DateTime": null
  },
  {
    "date": "2019/12/01",
    "heure": "19:16:47",
    "lon": "6.496152",
    "lat": "43.307471",
    "DateTime": null
  },
  {
    "date": "2019/12/01",
    "heure": "19:17:47",
    "lon": "6.471528",
    "lat": "43.29448",
    "DateTime": null
  },
  {
    "date": "2019/12/01",
    "heure": "19:22:22",
    "lon": "6.50558",
    "lat": "43.329816",
    "DateTime": null
  },
  {
    "date": "2019/12/01",
    "heure": "19:22:22",
    "lon": "6.50879",
    "lat": "43.326953",
    "DateTime": null
  },
  {
    "date": "2019/12/01",
    "heure": "19:23:50",
    "lon": "6.54365",
    "lat": "43.204257",
    "DateTime": null
  },
  {
    "date": "2019/12/01",
    "heure": "19:23:50",
    "lon": "6.546866",
    "lat": "43.342957",
    "DateTime": null
  },
  {
    "date": "2019/12/01",
    "heure": "19:23:50",
    "lon": "6.552617",
    "lat": "43.378111",
    "DateTime": null
  },
  {
    "date": "2019/12/01",
    "heure": "19:23:50",
    "lon": "6.554581",
    "lat": "43.4477",
    "DateTime": null
  },
  {
    "date": "2019/12/01",
    "heure": "19:23:50",
    "lon": "6.559029",
    "lat": "43.378713",
    "DateTime": null
  },
  {
    "date": "2019/12/01",
    "heure": "19:23:50",
    "lon": "6.566855",
    "lat": "43.473469",
    "DateTime": null
  },
  {
    "date": "2019/12/01",
    "heure": "19:25:51",
    "lon": "6.511258",
    "lat": "43.304893",
    "DateTime": null
  },
  {
    "date": "2019/12/01",
    "heure": "19:25:51",
    "lon": "6.525074",
    "lat": "43.356484",
    "DateTime": null
  },
  {
    "date": "2019/12/01",
    "heure": "19:25:51",
    "lon": "6.528103",
    "lat": "43.349019",
    "DateTime": null
  },
  {
    "date": "2019/12/01",
    "heure": "19:25:51",
    "lon": "6.538728",
    "lat": "43.34861",
    "DateTime": null
  },
  {
    "date": "2019/12/01",
    "heure": "19:25:51",
    "lon": "6.545848",
    "lat": "43.346624",
    "DateTime": null
  },
  {
    "date": "2019/12/01",
    "heure": "19:25:51",
    "lon": "6.54732",
    "lat": "43.342764",
    "DateTime": null
  },
  {
    "date": "2019/12/01",
    "heure": "19:27:12",
    "lon": "6.61417",
    "lat": "43.529041",
    "DateTime": null
  },
  {
    "date": "2019/12/01",
    "heure": "19:27:12",
    "lon": "6.652161",
    "lat": "43.396166",
    "DateTime": null
  },
  {
    "date": "2019/12/01",
    "heure": "19:27:12",
    "lon": "6.718988",
    "lat": "43.652168",
    "DateTime": null
  },
  {
    "date": "2019/12/01",
    "heure": "19:27:12",
    "lon": "6.746741",
    "lat": "43.630425",
    "DateTime": null
  },
  {
    "date": "2019/12/01",
    "heure": "19:27:12",
    "lon": "7.168145",
    "lat": "43.046671",
    "DateTime": null
  },
  {
    "date": "2019/12/01",
    "heure": "19:28:21",
    "lon": "6.53209",
    "lat": "43.368048",
    "DateTime": null
  },
  {
    "date": "2019/12/01",
    "heure": "19:28:21",
    "lon": "6.548563",
    "lat": "43.355506",
    "DateTime": null
  },
  {
    "date": "2019/12/01",
    "heure": "19:30:24",
    "lon": "6.428358",
    "lat": "43.299469",
    "DateTime": null
  },
  {
    "date": "2019/12/01",
    "heure": "19:30:24",
    "lon": "6.461877",
    "lat": "43.356655",
    "DateTime": null
  },
  {
    "date": "2019/12/01",
    "heure": "19:30:24",
    "lon": "6.47213",
    "lat": "43.335977",
    "DateTime": null
  },
  {
    "date": "2019/12/01",
    "heure": "19:30:24",
    "lon": "6.475648",
    "lat": "43.348679",
    "DateTime": null
  },
  {
    "date": "2019/12/01",
    "heure": "19:30:24",
    "lon": "6.479233",
    "lat": "43.346189",
    "DateTime": null
  },
  {
    "date": "2019/12/01",
    "heure": "19:30:24",
    "lon": "6.483343",
    "lat": "43.343256",
    "DateTime": null
  },
  {
    "date": "2019/12/01",
    "heure": "19:30:24",
    "lon": "6.485967",
    "lat": "43.339367",
    "DateTime": null
  },
  {
    "date": "2019/12/01",
    "heure": "19:30:24",
    "lon": "6.486773",
    "lat": "43.337966",
    "DateTime": null
  },
  {
    "date": "2019/12/01",
    "heure": "19:30:34",
    "lon": "6.608046",
    "lat": "43.458121",
    "DateTime": null
  },
  {
    "date": "2019/12/01",
    "heure": "19:30:34",
    "lon": "6.647882",
    "lat": "43.475672",
    "DateTime": null
  },
  {
    "date": "2019/12/01",
    "heure": "19:30:34",
    "lon": "6.64808",
    "lat": "43.486892",
    "DateTime": null
  },
  {
    "date": "2019/12/01",
    "heure": "19:31:37",
    "lon": "6.49374",
    "lat": "43.350815",
    "DateTime": null
  },
  {
    "date": "2019/12/01",
    "heure": "19:32:39",
    "lon": "6.546933",
    "lat": "43.400378",
    "DateTime": null
  },
  {
    "date": "2019/12/01",
    "heure": "19:32:39",
    "lon": "6.556626",
    "lat": "43.383393",
    "DateTime": null
  },
  {
    "date": "2019/12/01",
    "heure": "19:32:39",
    "lon": "6.569519",
    "lat": "43.406717",
    "DateTime": null
  },
  {
    "date": "2019/12/01",
    "heure": "19:38:31",
    "lon": "6.603546",
    "lat": "43.394075",
    "DateTime": null
  },
  {
    "date": "2019/12/01",
    "heure": "19:38:31",
    "lon": "6.612362",
    "lat": "43.388945",
    "DateTime": null
  },
  {
    "date": "2019/12/01",
    "heure": "19:38:31",
    "lon": "6.612919",
    "lat": "43.389963",
    "DateTime": null
  },
  {
    "date": "2019/12/01",
    "heure": "19:39:56",
    "lon": "6.587754",
    "lat": "43.434157",
    "DateTime": null
  },
  {
    "date": "2019/12/01",
    "heure": "19:39:56",
    "lon": "6.594795",
    "lat": "43.414006",
    "DateTime": null
  },
  {
    "date": "2019/12/01",
    "heure": "19:39:56",
    "lon": "6.608926",
    "lat": "43.38923",
    "DateTime": null
  },
  {
    "date": "2019/12/01",
    "heure": "19:41:30",
    "lon": "6.605018",
    "lat": "43.476734",
    "DateTime": null
  },
  {
    "date": "2019/12/01",
    "heure": "19:42:17",
    "lon": "6.628015",
    "lat": "43.426212",
    "DateTime": null
  },
  {
    "date": "2019/12/01",
    "heure": "19:43:32",
    "lon": "6.581082",
    "lat": "43.405797",
    "DateTime": null
  },
  {
    "date": "2019/12/01",
    "heure": "19:43:32",
    "lon": "6.597562",
    "lat": "43.412724",
    "DateTime": null
  },
  {
    "date": "2019/12/01",
    "heure": "19:45:25",
    "lon": "6.575478",
    "lat": "43.376946",
    "DateTime": null
  },
  {
    "date": "2019/12/01",
    "heure": "19:47:26",
    "lon": "6.616199",
    "lat": "43.425073",
    "DateTime": null
  },
  {
    "date": "2019/12/01",
    "heure": "19:47:26",
    "lon": "6.619449",
    "lat": "43.429012",
    "DateTime": null
  },
  {
    "date": "2019/12/01",
    "heure": "19:48:18",
    "lon": "6.610174",
    "lat": "43.408056",
    "DateTime": null
  },
  {
    "date": "2019/12/01",
    "heure": "19:48:18",
    "lon": "6.614102",
    "lat": "43.401047",
    "DateTime": null
  },
  {
    "date": "2019/12/01",
    "heure": "19:48:18",
    "lon": "6.623201",
    "lat": "43.417375",
    "DateTime": null
  },
  {
    "date": "2019/12/01",
    "heure": "19:48:59",
    "lon": "-2.82713",
    "lat": "43.698972",
    "DateTime": null
  },
  {
    "date": "2019/12/01",
    "heure": "19:48:59",
    "lon": "-2.982869",
    "lat": "43.54146",
    "DateTime": null
  },
  {
    "date": "2019/12/01",
    "heure": "19:49:00",
    "lon": "6.620868",
    "lat": "43.41043",
    "DateTime": null
  },
  {
    "date": "2019/12/01",
    "heure": "19:49:48",
    "lon": "6.511003",
    "lat": "43.319938",
    "DateTime": null
  },
  {
    "date": "2019/12/01",
    "heure": "19:50:30",
    "lon": "6.56426",
    "lat": "43.333222",
    "DateTime": null
  },
  {
    "date": "2019/12/01",
    "heure": "19:50:30",
    "lon": "6.621865",
    "lat": "43.437448",
    "DateTime": null
  },
  {
    "date": "2019/12/01",
    "heure": "19:50:30",
    "lon": "6.629718",
    "lat": "43.438901",
    "DateTime": null
  },
  {
    "date": "2019/12/01",
    "heure": "19:50:30",
    "lon": "6.632019",
    "lat": "43.485791",
    "DateTime": null
  },
  {
    "date": "2019/12/01",
    "heure": "19:50:30",
    "lon": "6.643207",
    "lat": "43.427653",
    "DateTime": null
  },
  {
    "date": "2019/12/01",
    "heure": "19:50:30",
    "lon": "6.650615",
    "lat": "43.38074",
    "DateTime": null
  },
  {
    "date": "2019/12/01",
    "heure": "19:51:45",
    "lon": "6.610531",
    "lat": "43.453615",
    "DateTime": null
  },
  {
    "date": "2019/12/01",
    "heure": "19:51:45",
    "lon": "6.613281",
    "lat": "43.45633",
    "DateTime": null
  },
  {
    "date": "2019/12/01",
    "heure": "19:51:45",
    "lon": "6.616635",
    "lat": "43.475995",
    "DateTime": null
  },
  {
    "date": "2019/12/01",
    "heure": "19:51:45",
    "lon": "6.622871",
    "lat": "43.458031",
    "DateTime": null
  },
  {
    "date": "2019/12/01",
    "heure": "19:51:45",
    "lon": "6.622993",
    "lat": "43.445363",
    "DateTime": null
  },
  {
    "date": "2019/12/01",
    "heure": "19:51:45",
    "lon": "6.62477",
    "lat": "43.465105",
    "DateTime": null
  },
  {
    "date": "2019/12/01",
    "heure": "19:51:45",
    "lon": "6.626412",
    "lat": "43.431736",
    "DateTime": null
  },
  {
    "date": "2019/12/01",
    "heure": "19:52:14",
    "lon": "6.503529",
    "lat": "43.246696",
    "DateTime": null
  },
  {
    "date": "2019/12/01",
    "heure": "19:52:14",
    "lon": "6.640537",
    "lat": "43.437665",
    "DateTime": null
  },
  {
    "date": "2019/12/01",
    "heure": "19:52:14",
    "lon": "6.653275",
    "lat": "43.436872",
    "DateTime": null
  },
  {
    "date": "2019/12/01",
    "heure": "19:54:33",
    "lon": "6.659207",
    "lat": "43.456335",
    "DateTime": null
  },
  {
    "date": "2019/12/01",
    "heure": "19:55:51",
    "lon": "6.663423",
    "lat": "43.46309",
    "DateTime": null
  },
  {
    "date": "2019/12/01",
    "heure": "19:59:37",
    "lon": "6.681832",
    "lat": "43.458055",
    "DateTime": null
  },
  {
    "date": "2019/12/01",
    "heure": "20:01:54",
    "lon": "6.692093",
    "lat": "43.473076",
    "DateTime": null
  },
  {
    "date": "2019/12/01",
    "heure": "20:01:54",
    "lon": "6.697582",
    "lat": "43.486316",
    "DateTime": null
  },
  {
    "date": "2019/12/01",
    "heure": "20:01:54",
    "lon": "6.697664",
    "lat": "43.476304",
    "DateTime": null
  },
  {
    "date": "2019/12/01",
    "heure": "20:01:54",
    "lon": "6.705115",
    "lat": "43.445328",
    "DateTime": null
  },
  {
    "date": "2019/12/01",
    "heure": "20:01:54",
    "lon": "7.109779",
    "lat": "43.758743",
    "DateTime": null
  },
  {
    "date": "2019/12/01",
    "heure": "20:04:24",
    "lon": "6.682325",
    "lat": "43.473436",
    "DateTime": null
  },
  {
    "date": "2019/12/01",
    "heure": "20:04:24",
    "lon": "6.699104",
    "lat": "43.485428",
    "DateTime": null
  },
  {
    "date": "2019/12/01",
    "heure": "20:04:24",
    "lon": "6.871187",
    "lat": "43.598091",
    "DateTime": null
  },
  {
    "date": "2019/12/01",
    "heure": "20:08:08",
    "lon": "6.745564",
    "lat": "43.377875",
    "DateTime": null
  },
  {
    "date": "2019/12/01",
    "heure": "20:13:55",
    "lon": "6.733473",
    "lat": "43.434438",
    "DateTime": null
  },
  {
    "date": "2019/12/01",
    "heure": "20:21:27",
    "lon": "6.707359",
    "lat": "43.37554",
    "DateTime": null
  },
  {
    "date": "2019/12/01",
    "heure": "20:21:27",
    "lon": "6.78823",
    "lat": "43.523586",
    "DateTime": null
  },
  {
    "date": "2019/12/01",
    "heure": "20:21:27",
    "lon": "6.800835",
    "lat": "43.444546",
    "DateTime": null
  },
  {
    "date": "2019/12/01",
    "heure": "20:21:27",
    "lon": "6.807789",
    "lat": "43.462782",
    "DateTime": null
  },
  {
    "date": "2019/12/01",
    "heure": "20:21:27",
    "lon": "6.81098",
    "lat": "43.486228",
    "DateTime": null
  },
  {
    "date": "2019/12/01",
    "heure": "20:21:27",
    "lon": "6.815209",
    "lat": "43.439682",
    "DateTime": null
  },
  {
    "date": "2019/12/01",
    "heure": "20:21:27",
    "lon": "6.826556",
    "lat": "43.424779",
    "DateTime": null
  },
  {
    "date": "2019/12/01",
    "heure": "20:21:27",
    "lon": "6.826945",
    "lat": "43.483901",
    "DateTime": null
  },
  {
    "date": "2019/12/01",
    "heure": "20:21:27",
    "lon": "6.843861",
    "lat": "43.501158",
    "DateTime": null
  },
  {
    "date": "2019/12/01",
    "heure": "20:21:27",
    "lon": "6.849827",
    "lat": "43.549456",
    "DateTime": null
  },
  {
    "date": "2019/12/01",
    "heure": "20:40:57",
    "lon": "6.68927",
    "lat": "43.387924",
    "DateTime": null
  },
  {
    "date": "2019/12/01",
    "heure": "20:40:57",
    "lon": "6.695769",
    "lat": "43.362976",
    "DateTime": null
  },
  {
    "date": "2019/12/01",
    "heure": "20:40:57",
    "lon": "6.69792",
    "lat": "43.36279",
    "DateTime": null
  },
  {
    "date": "2019/12/01",
    "heure": "20:40:57",
    "lon": "6.700571",
    "lat": "43.367802",
    "DateTime": null
  },
  {
    "date": "2019/12/01",
    "heure": "20:41:57",
    "lon": "6.50521",
    "lat": "43.296127",
    "DateTime": null
  },
  {
    "date": "2019/12/01",
    "heure": "20:41:57",
    "lon": "6.636736",
    "lat": "43.227073",
    "DateTime": null
  },
  {
    "date": "2019/12/01",
    "heure": "20:41:57",
    "lon": "6.69914",
    "lat": "43.375349",
    "DateTime": null
  },
  {
    "date": "2019/12/01",
    "heure": "20:42:49",
    "lon": "6.688031",
    "lat": "43.350155",
    "DateTime": null
  },
  {
    "date": "2019/12/01",
    "heure": "20:45:58",
    "lon": "6.619806",
    "lat": "43.199059",
    "DateTime": null
  },
  {
    "date": "2019/12/01",
    "heure": "20:45:58",
    "lon": "6.621954",
    "lat": "43.20303",
    "DateTime": null
  },
  {
    "date": "2019/12/01",
    "heure": "20:47:39",
    "lon": "6.410802",
    "lat": "43.089607",
    "DateTime": null
  },
  {
    "date": "2019/12/01",
    "heure": "20:47:39",
    "lon": "6.589049",
    "lat": "43.221437",
    "DateTime": null
  },
  {
    "date": "2019/12/01",
    "heure": "20:47:39",
    "lon": "6.590007",
    "lat": "43.226411",
    "DateTime": null
  },
  {
    "date": "2019/12/01",
    "heure": "20:47:39",
    "lon": "6.601769",
    "lat": "43.223141",
    "DateTime": null
  },
  {
    "date": "2019/12/01",
    "heure": "21:00:32",
    "lon": "6.820103",
    "lat": "43.415595",
    "DateTime": null
  },
  {
    "date": "2019/12/01",
    "heure": "21:26:41",
    "lon": "6.611276",
    "lat": "43.000879",
    "DateTime": null
  },
  {
    "date": "2019/12/01",
    "heure": "21:26:41",
    "lon": "6.630095",
    "lat": "42.97213",
    "DateTime": null
  },
  {
    "date": "2019/12/01",
    "heure": "21:26:45",
    "lon": "6.929025",
    "lat": "43.332391",
    "DateTime": null
  },
  {
    "date": "2019/12/01",
    "heure": "21:26:45",
    "lon": "6.959285",
    "lat": "43.374408",
    "DateTime": null
  },
  {
    "date": "2019/12/01",
    "heure": "21:26:45",
    "lon": "7.050649",
    "lat": "43.474453",
    "DateTime": null
  },
  {
    "date": "2019/12/01",
    "heure": "21:26:45",
    "lon": "7.065485",
    "lat": "43.488213",
    "DateTime": null
  },
  {
    "date": "2019/12/01",
    "heure": "21:47:55",
    "lon": "6.898337",
    "lat": "43.023464",
    "DateTime": null
  },
  {
    "date": "2019/12/01",
    "heure": "21:51:56",
    "lon": "6.866813",
    "lat": "43.184349",
    "DateTime": null
  },
  {
    "date": "2019/12/01",
    "heure": "21:54:51",
    "lon": "6.707176",
    "lat": "43.061355",
    "DateTime": null
  },
  {
    "date": "2019/12/01",
    "heure": "21:55:21",
    "lon": "6.939008",
    "lat": "43.236476",
    "DateTime": null
  },
  {
    "date": "2019/12/01",
    "heure": "21:55:21",
    "lon": "6.959098",
    "lat": "43.236845",
    "DateTime": null
  },
  {
    "date": "2019/12/01",
    "heure": "21:55:26",
    "lon": "6.961605",
    "lat": "43.209401",
    "DateTime": null
  },
  {
    "date": "2019/12/01",
    "heure": "22:13:10",
    "lon": "6.939389",
    "lat": "43.219377",
    "DateTime": null
  },
  {
    "date": "2019/12/01",
    "heure": "22:13:10",
    "lon": "6.950188",
    "lat": "43.23336",
    "DateTime": null
  },
  {
    "date": "2019/12/01",
    "heure": "22:13:11",
    "lon": "6.914018",
    "lat": "43.231862",
    "DateTime": null
  },
  {
    "date": "2019/12/01",
    "heure": "22:13:11",
    "lon": "6.914185",
    "lat": "43.259091",
    "DateTime": null
  },
  {
    "date": "2019/12/01",
    "heure": "22:16:46",
    "lon": "6.897146",
    "lat": "43.226036",
    "DateTime": null
  },
  {
    "date": "2019/12/01",
    "heure": "22:16:46",
    "lon": "6.906553",
    "lat": "43.23635",
    "DateTime": null
  },
  {
    "date": "2019/12/01",
    "heure": "22:16:46",
    "lon": "6.917222",
    "lat": "43.236532",
    "DateTime": null
  },
  {
    "date": "2019/12/01",
    "heure": "22:18:42",
    "lon": "6.936485",
    "lat": "43.222444",
    "DateTime": null
  },
  {
    "date": "2019/12/01",
    "heure": "22:18:42",
    "lon": "6.939986",
    "lat": "43.214056",
    "DateTime": null
  },
  {
    "date": "2019/12/01",
    "heure": "22:20:40",
    "lon": "6.815083",
    "lat": "43.156706",
    "DateTime": null
  },
  {
    "date": "2019/12/01",
    "heure": "22:20:40",
    "lon": "6.829749",
    "lat": "43.160705",
    "DateTime": null
  },
  {
    "date": "2019/12/01",
    "heure": "22:26:32",
    "lon": "7.099556",
    "lat": "43.403057",
    "DateTime": null
  },
  {
    "date": "2019/12/01",
    "heure": "22:28:14",
    "lon": "6.857953",
    "lat": "43.098965",
    "DateTime": null
  },
  {
    "date": "2019/12/01",
    "heure": "22:29:03",
    "lon": "6.85886",
    "lat": "43.217433",
    "DateTime": null
  },
  {
    "date": "2019/12/01",
    "heure": "22:29:42",
    "lon": "6.764528",
    "lat": "43.022057",
    "DateTime": null
  },
  {
    "date": "2019/12/01",
    "heure": "22:29:42",
    "lon": "6.832903",
    "lat": "43.122463",
    "DateTime": null
  },
  {
    "date": "2019/12/01",
    "heure": "22:29:42",
    "lon": "6.859003",
    "lat": "43.111653",
    "DateTime": null
  },
  {
    "date": "2019/12/01",
    "heure": "22:39:29",
    "lon": "6.889785",
    "lat": "43.138221",
    "DateTime": null
  },
  {
    "date": "2019/12/01",
    "heure": "22:39:29",
    "lon": "6.906627",
    "lat": "43.142937",
    "DateTime": null
  },
  {
    "date": "2019/12/01",
    "heure": "22:39:29",
    "lon": "6.908248",
    "lat": "43.152371",
    "DateTime": null
  },
  {
    "date": "2019/12/01",
    "heure": "22:44:17",
    "lon": "6.915702",
    "lat": "43.160545",
    "DateTime": null
  },
  {
    "date": "2019/12/01",
    "heure": "22:44:17",
    "lon": "6.92392",
    "lat": "43.192031",
    "DateTime": null
  },
  {
    "date": "2019/12/01",
    "heure": "22:44:17",
    "lon": "6.929637",
    "lat": "43.134139",
    "DateTime": null
  },
  {
    "date": "2019/12/01",
    "heure": "22:44:17",
    "lon": "6.932583",
    "lat": "43.156539",
    "DateTime": null
  },
  {
    "date": "2019/12/01",
    "heure": "22:44:17",
    "lon": "6.936617",
    "lat": "43.151623",
    "DateTime": null
  },
  {
    "date": "2019/12/01",
    "heure": "22:44:17",
    "lon": "6.940886",
    "lat": "43.145251",
    "DateTime": null
  },
  {
    "date": "2019/12/01",
    "heure": "22:54:47",
    "lon": "7.382203",
    "lat": "43.701204",
    "DateTime": null
  },
  {
    "date": "2019/12/01",
    "heure": "22:54:47",
    "lon": "7.526378",
    "lat": "43.671094",
    "DateTime": null
  },
  {
    "date": "2019/12/01",
    "heure": "23:03:25",
    "lon": "7.188109",
    "lat": "43.295297",
    "DateTime": null
  },
  {
    "date": "2019/12/01",
    "heure": "23:14:50",
    "lon": "7.126561",
    "lat": "43.133373",
    "DateTime": null
  },
  {
    "date": "2019/12/01",
    "heure": "23:14:50",
    "lon": "7.127292",
    "lat": "43.110955",
    "DateTime": null
  },
  {
    "date": "2019/12/01",
    "heure": "23:17:49",
    "lon": "7.135229",
    "lat": "43.128937",
    "DateTime": null
  },
  {
    "date": "2019/12/01",
    "heure": "23:17:49",
    "lon": "7.13574",
    "lat": "43.115453",
    "DateTime": null
  },
  {
    "date": "2019/12/01",
    "heure": "23:23:40",
    "lon": "7.02125",
    "lat": "42.853133",
    "DateTime": null
  },
  {
    "date": "2019/12/01",
    "heure": "23:23:41",
    "lon": "7.120602",
    "lat": "43.046056",
    "DateTime": null
  }
]